fedml_gcp/__init__.py
fedml_gcp/build_and_push.sh
fedml_gcp/dbconnection.py
fedml_gcp/dwcgcp.py
fedml_gcp/install_kubectl.sh
fedml_gcp/logger.py
fedml_gcp/model.py
fedml_gcp/script_generator.py
fedml_gcp-2.1.1.data/scripts/build_and_push.sh
fedml_gcp-2.1.1.data/scripts/install_kubectl.sh
fedml_gcp-2.1.1.dist-info/METADATA
fedml_gcp-2.1.1.dist-info/WHEEL
fedml_gcp-2.1.1.dist-info/top_level.txt
fedml_gcp-2.1.1.dist-info/RECORD
