Metadata-Version: 2.1
Name: fedml-gcp
Version: 2.1.1
Summary: A python library for building machine learning models on Google Cloud Platform using a federated data source
Author: SAP SE
License: Apache License 2.0
Classifier: Programming Language :: Python :: 3
Classifier: Operating System :: OS Independent
Requires-Python: >=3
Requires-Dist: hdbcli
Requires-Dist: google
Requires-Dist: google-cloud-aiplatform
Requires-Dist: pyyaml
Requires-Dist: requests
Requires-Dist: numpy
Requires-Dist: pandas
